LICENSE.txt
README.md
setup.cfg
setup.py
ultralight/__init__.py
ultralight/exceptions.py
ultralight/loader.py
ultralight/types.py
ultralight/ultralight.py
ultralight/utils.py
ultralight.egg-info/PKG-INFO
ultralight.egg-info/SOURCES.txt
ultralight.egg-info/dependency_links.txt
ultralight.egg-info/not-zip-safe
ultralight.egg-info/requires.txt
ultralight.egg-info/top_level.txt