Metadata-Version: 2.1
Name: ultralight
Version: 2.0.0
Summary: Ultra Light Fast Generic Face Detector 👨‍👩‍👧‍👦🖼
Home-page: https://github.com/abionics/UltraLight
Author: Alex Ermolaev
Author-email: abionics.dev@gmail.com
License: MIT
Keywords: face detection ai ultra light
Platform: UNKNOWN
Classifier: Intended Audience :: Developers
Classifier: Intended Audience :: Education
Classifier: Intended Audience :: Science/Research
Classifier: License :: OSI Approved :: MIT License
Classifier: Operating System :: OS Independent
Classifier: Programming Language :: Python :: 3
Classifier: Programming Language :: Python :: 3.9
Classifier: Programming Language :: Python :: 3.10
Classifier: Programming Language :: Python :: 3.11
Classifier: Topic :: Scientific/Engineering :: Artificial Intelligence
Classifier: Topic :: Scientific/Engineering :: Image Processing
Classifier: Topic :: Scientific/Engineering :: Image Recognition
Classifier: Topic :: Software Development :: Libraries :: Python Modules
Classifier: Typing :: Typed
License-File: LICENSE.txt
